fsm_0/rtl/fsm.v
module fsm
(
	input clk_i,
	input reset_i,
	input data_i,
	output reg match_o
);

parameter IDLE 	= 1'd0;
parameter S1	= 1'd1;

reg next_state;
reg curr_state;

always@(posedge clk_i or negedge reset_i)
begin
	if(!reset_i)
	curr_state <= 2'd0;
	else
	curr_state <= next_state;
end

always@ *
begin
match_o = 1'd0;
next_state = IDLE;
case (curr_state)
	IDLE:
	if(data_i)
		next_state = S1;
	S1:
	begin
	if(data_i)
		next_state = S1;
	else
		match_o = 1'd1;
	end
endcase
end
endmodule

fsm_0/tb/tb_sample.v
module tb();
reg clk_i, reset_i, data_i;
wire match_o;
fsm pd0(.*);
initial
begin
	$dumpfile("sample.vcd");
	$dumpvars;
	clk_i = 1'd0;
	forever #5 clk_i = ~clk_i;
end

initial
begin
#0 reset_i <= 1'd1;
#5 reset_i <= 1'd0;
data_i <= 1'd0;
#10 reset_i <= 1'd1;
#10;
#10 data_i <= 1'd0;
#10 data_i <= 1'd1;
#10 data_i <= 1'd0;
#10 data_i <= 1'd0;
#10 data_i <= 1'd1;
#10 data_i <= 1'd0;
#10 data_i <= 1'd1;
#10 data_i <= 1'd1;
#10 data_i <= 1'd0;
#10 data_i <= 1'd1;
#20;
$finish;
end
endmodule

fsm_0/tb/sample.vcd
$date
	Thu Jul 25 21:04:45 2024
$end
$version
	Icarus Verilog
$end
$timescale
	1s
$end
$scope module tb $end
$var wire 1 ! match_o $end
$var reg 1 " clk_i $end
$var reg 1 # data_i $end
$var reg 1 $ reset_i $end
$scope module pd0 $end
$var wire 1 " clk_i $end
$var wire 1 # data_i $end
$var wire 1 $ reset_i $end
$var reg 1 % curr_state $end
$var reg 1 ! match_o $end
$var reg 1 & next_state $end
$upscope $end
$upscope $end
$enddefinitions $end
#0
$dumpvars
x&
x%
1$
x#
0"
x!
$end
#5
0%
0&
0!
0#
0$
1"
#10
0"
#15
1$
1"
#20
0"
#25
1"
#30
0"
#35
1"
#40
0"
#45
1&
1#
1"
#50
0"
#55
1!
0&
1%
0#
1"
#60
0"
#65
0!
0%
1"
#70
0"
#75
1&
1#
1"
#80
0"
#85
1!
0&
1%
0#
1"
#90
0"
#95
1&
0!
0%
1#
1"
#100
0"
#105
1&
1%
1"
#110
0"
#115
1!
0&
0#
1"
#120
0"
#125
1&
0!
0%
1#
1"
#130
0"
#135
1&
1%
1"
